haplot/__init__.py
haplot/chart.py
haplot/data.py
haplot/theme.py
haplot/utils.py
haplot-0.0.2.dist-info/LICENSE
haplot-0.0.2.dist-info/METADATA
haplot-0.0.2.dist-info/WHEEL
haplot-0.0.2.dist-info/top_level.txt
haplot-0.0.2.dist-info/RECORD
