Metadata-Version: 2.1
Name: haplot
Version: 0.0.2
Summary: A package for genomic data visualization
Home-page: https://github.com/swu1019lab/haplot
Author: XiaoDong Li
Author-email: lxd1997xy@163.com
License: BSD 3-clause
Platform: UNKNOWN
Requires-Python: >=3.10
License-File: LICENSE
Requires-Dist: numpy (>=1.22.3)
Requires-Dist: pandas (>=1.4.2)
Requires-Dist: matplotlib (>=3.6.2)
Requires-Dist: scipy (>=1.9.3)
Requires-Dist: geopandas (>=0.13.2)
Requires-Dist: networkx (>=3.1)
